privforge/__init__.py
privforge/privforge.py
privforge/Exploits/__init__.py
privforge/Exploits/backdoor.py
privforge/Exploits/nfs_exploit.py
privforge/Exploits/path_exploit.py
privforge/OfflineGtfo/__init__.py
privforge/OfflineGtfo/functions_handler.py
privforge/OfflineGtfo/handle_choice.py
privforge/OfflineGtfo/menu.py
privforge/OfflineGtfo/parse_file_to_json.py
privforge/OfflineGtfo/search_binary.py
privforge/Tools/__init__.py
privforge/Tools/offline_gtfo.py
privforge-1.2.0.dist-info/licenses/LICENSE
privforge-1.2.0.dist-info/METADATA
privforge-1.2.0.dist-info/WHEEL
privforge-1.2.0.dist-info/entry_points.txt
privforge-1.2.0.dist-info/top_level.txt
privforge-1.2.0.dist-info/RECORD
